LICENSE
MANIFEST.in
README.rst
setup.py
src/pwutils/__init__.py
src/pwutils/defs.py
src/pwutils/pcrypt.py
src/pwutils/pwgen.py
src/pwutils/utils.py
src/pwutils.egg-info/PKG-INFO
src/pwutils.egg-info/SOURCES.txt
src/pwutils.egg-info/dependency_links.txt
src/pwutils.egg-info/entry_points.txt
src/pwutils.egg-info/top_level.txt
src/pwutils.egg-info/zip-safe