Metadata-Version: 1.1
Name: pwutils
Version: 0.0.1
Summary: tools for manipulating passwords
Home-page: https://github.com/beli-sk/pwutils
Author: Michal Belica
Author-email: devel@beli.sk
License: GPL-3
Keywords: password
Platform: UNKNOWN
Classifier: Development Status :: 3 - Alpha
Classifier: Environment :: Console
Classifier: Intended Audience :: System Administrators
Classifier: License :: OSI Approved :: GNU General Public License v3 or later (GPLv3+)
Classifier: Operating System :: POSIX :: Linux
Classifier: Programming Language :: Python :: 3
